tmagent/__init__.py
tmagent/config.py
tmagent/display.py
tmagent/i18n.py
tmagent/main.py
tmagent/sessions.py
tmagent/utils.py
tmagent-0.1.1.dist-info/licenses/LICENSE
tmagent-0.1.1.dist-info/METADATA
tmagent-0.1.1.dist-info/WHEEL
tmagent-0.1.1.dist-info/entry_points.txt
tmagent-0.1.1.dist-info/top_level.txt
tmagent-0.1.1.dist-info/RECORD
