Metadata-Version: 2.4
Name: tmagent
Version: 0.1.1
Summary: An interactive CLI tool for managing tmate sessions with Telegram notifications
Author-email: Aleksei Svetlov <svetlovtech@aabee.tech>
License-Expression: MIT
Project-URL: Homepage, https://github.com/aabee-tech/tmagent
Project-URL: Repository, https://github.com/aabee-tech/tmagent
Classifier: Programming Language :: Python :: 3
Classifier: Operating System :: OS Independent
Classifier: Topic :: Terminals
Classifier: Topic :: Utilities
Requires-Python: >=3.10
License-File: LICENSE
Requires-Dist: rich
Requires-Dist: questionary
Requires-Dist: qrcode
Requires-Dist: pyperclip
Requires-Dist: requests
Provides-Extra: dev
Requires-Dist: wily; extra == "dev"
Requires-Dist: bandit; extra == "dev"
Requires-Dist: ruff; extra == "dev"
Requires-Dist: pytest; extra == "dev"
Requires-Dist: pytest-cov; extra == "dev"
Requires-Dist: mypy; extra == "dev"
Requires-Dist: build; extra == "dev"
Requires-Dist: twine; extra == "dev"
Dynamic: license-file
